{
  "sections": {
    "section_image_slider_mWkXJH": {
      "type": "section-image-slider",
      "blocks": {
        "slide_iayDqF": {
          "type": "slide",
          "settings": {
            "desktop_image": "shopify:\/\/shop_images\/White_e433301a-5494-45ea-9236-d293e872702c.png",
            "mobile_image": "shopify:\/\/shop_images\/Soft_Blue.png",
            "link": "shopify:\/\/collections\/сватбени-рокли"
          }
        },
        "slide_xGF3nG": {
          "type": "slide",
          "settings": {
            "desktop_image": "shopify:\/\/shop_images\/Soft_Purple.png",
            "mobile_image": "shopify:\/\/shop_images\/Pink_e685a450-d4c3-428b-b29b-5fdd16473121.png",
            "link": "shopify:\/\/collections\/сватбени-рокли"
          }
        }
      },
      "block_order": [
        "slide_iayDqF",
        "slide_xGF3nG"
      ],
      "settings": {
        "padding_top": 36,
        "padding_bottom": 0
      }
    },
    "section_products_release_BWwRmf": {
      "type": "section-products-release",
      "settings": {
        "heading": "Най-продавани",
        "products": [
          "дамска-рокля-summer-allure-3-в-цвят-бяло",
          "дамска-рокля-summer-allure-3",
          "дамска-рокля-night-allure-в-черен-цвят",
          "дамска-рокля-night-allure-в-цвят-тъмно-зелено",
          "дамска-рокля-midnight-elegance"
        ],
        "image_ratio": "portrait",
        "image_shape": "default",
        "padding_top": 36,
        "padding_bottom": 36
      }
    },
    "section_collection_release_bgwtFL": {
      "type": "section-collection-release",
      "settings": {
        "enable_slider_on_desktop": false,
        "heading": "Галерия \/ Collection 1",
        "collection": "all-products",
        "image_ratio": "portrait",
        "image_shape": "default",
        "padding_top": 0,
        "padding_bottom": 0
      }
    },
    "section_image_slider_teD4AM": {
      "type": "section-image-slider",
      "settings": {
        "padding_top": 0,
        "padding_bottom": 0
      }
    },
    "section_collection_release_kXrKtk": {
      "type": "section-collection-release",
      "settings": {
        "enable_slider_on_desktop": false,
        "heading": "Collection 2",
        "collection": "all-products",
        "image_ratio": "portrait",
        "image_shape": "default",
        "padding_top": 36,
        "padding_bottom": 0
      }
    },
    "section_collections_release_3Gcj8x": {
      "type": "section-collections-release",
      "settings": {
        "collections": [
          "сватбени-рокли",
          "летни-рокли",
          "официални-рокли"
        ],
        "padding_top": 36,
        "padding_bottom": 36
      }
    },
    "section_collection_release_eth8Bn": {
      "type": "section-collection-release",
      "settings": {
        "enable_slider_on_desktop": true,
        "heading": "Аксесоари",
        "collection": "летни-рокли",
        "image_ratio": "adapt",
        "image_shape": "default",
        "padding_top": 36,
        "padding_bottom": 0
      }
    },
    "section_collection_release_PNPJcR": {
      "type": "section-collection-release",
      "settings": {
        "enable_slider_on_desktop": true,
        "heading": "Чанти",
        "collection": "летни-рокли",
        "image_ratio": "adapt",
        "image_shape": "default",
        "padding_top": 0,
        "padding_bottom": 0
      }
    },
    "section_collection_release_t8MUYg": {
      "type": "section-collection-release",
      "settings": {
        "enable_slider_on_desktop": true,
        "heading": "Обеци",
        "collection": "летни-рокли",
        "image_ratio": "adapt",
        "image_shape": "default",
        "padding_top": 0,
        "padding_bottom": 36
      }
    }
  },
  "order": [
    "section_image_slider_mWkXJH",
    "section_products_release_BWwRmf",
    "section_collection_release_bgwtFL",
    "section_image_slider_teD4AM",
    "section_collection_release_kXrKtk",
    "section_collections_release_3Gcj8x",
    "section_collection_release_eth8Bn",
    "section_collection_release_PNPJcR",
    "section_collection_release_t8MUYg"
  ]
}
